{"branch":"OBA punt Ganzenhoef","lastSync":1767997452420,"total":5,"pages":1,"items":[{"id":"|evenementen|2067817","title":"Online Taalcafé","location":"OBA Online","start":"2026-01-09T09:30:00.000Z","week":"b_thisweek","branch":"OBA punt Ganzenhoef"},{"id":"|evenementen|2067739","title":"Online Meeleesclub","location":"OBA Online","start":"2026-01-13T09:30:00.000Z","week":"c_nextweek","branch":"OBA punt Ganzenhoef"},{"id":"|evenementen|2131100","title":"Boek op schoot 2+","location":"Jeugdhoek","start":"2026-01-14T09:00:00.000Z","week":"c_nextweek","branch":"OBA punt Ganzenhoef"},{"id":"|evenementen|2062206","title":"Spreekuur: Hulp bij digitaal","location":"Open ruimte","start":"2026-01-14T12:30:00.000Z","week":"c_nextweek","branch":"OBA punt Ganzenhoef"},{"id":"|evenementen|2067818","title":"Online Taalcafé","location":"OBA Online","start":"2026-01-16T09:30:00.000Z","week":"c_nextweek","branch":"OBA punt Ganzenhoef"}],"counts":{"b_thisweek":1,"c_nextweek":4},"error":null}