{"branch":"OBA Postjesweg","lastSync":1770460177886,"total":5,"pages":1,"items":[{"id":"|evenementen|2067743","title":"Online Meeleesclub","location":"OBA Online","start":"2026-02-10T09:30:00.000Z","week":"c_nextweek","branch":"OBA Postjesweg"},{"id":"|evenementen|2163919","title":"Vlaggetjes maken met het Stadsdorp","location":"Open ruimte","start":"2026-02-11T18:15:00.000Z","week":"c_nextweek","branch":"OBA Postjesweg"},{"id":"|evenementen|2163948","title":"Bridge- en spelletjesavond Stadsdorp Slotervaart Noord","location":"Open ruimte","start":"2026-02-12T18:30:00.000Z","week":"c_nextweek","branch":"OBA Postjesweg"},{"id":"|evenementen|2133641","title":"Boek op schoot 2+","location":"Open ruimte","start":"2026-02-13T09:00:00.000Z","week":"c_nextweek","branch":"OBA Postjesweg"},{"id":"|evenementen|2067822","title":"Online Taalcafé","location":"OBA Online","start":"2026-02-13T09:30:00.000Z","week":"c_nextweek","branch":"OBA Postjesweg"}],"counts":{"b_thisweek":0,"c_nextweek":5},"error":null}