{"branch":"OBA Bos en Lommer","lastSync":1772181891652,"total":7,"pages":1,"items":[{"id":"|evenementen|2067824","title":"Online Taalcafé","location":"OBA Online","start":"2026-02-27T09:30:00.000Z","week":"b_thisweek","branch":"OBA Bos en Lommer"},{"id":"|evenementen|2067759","title":"Online Meeleesclub","location":"OBA Online","start":"2026-03-03T09:30:00.000Z","week":"c_nextweek","branch":"OBA Bos en Lommer"},{"id":"|evenementen|2061686","title":"Spreekuur: Hulp bij digitaal","location":"Open ruimte","start":"2026-03-04T09:00:00.000Z","week":"c_nextweek","branch":"OBA Bos en Lommer"},{"id":"|evenementen|2066300","title":"Oefenuur","location":"Open ruimte","start":"2026-03-04T09:00:00.000Z","week":"c_nextweek","branch":"OBA Bos en Lommer"},{"id":"|evenementen|2105908","title":"Voorleesatelier 5+","location":"Jeugdhoek Dolfje","start":"2026-03-04T14:30:00.000Z","week":"c_nextweek","branch":"OBA Bos en Lommer"},{"id":"|evenementen|2115026","title":"Cursus: Veilig op jouw apparaat (bijeenkomst 2)","location":"Open ruimte","start":"2026-03-05T13:00:00.000Z","week":"c_nextweek","branch":"OBA Bos en Lommer"},{"id":"|evenementen|2067825","title":"Online Taalcafé","location":"OBA Online","start":"2026-03-06T09:30:00.000Z","week":"c_nextweek","branch":"OBA Bos en Lommer"}],"counts":{"b_thisweek":1,"c_nextweek":6},"error":null}