{"branch":"OBA Van der Pek","lastSync":1772763733156,"total":8,"pages":1,"items":[{"id":"|evenementen|2148235","title":"Conversatielessen","location":"Open ruimte","start":"2026-03-05T09:00:00.000Z","week":"b_thisweek","branch":"OBA Van der Pek"},{"id":"|evenementen|2133883","title":"Boek op schoot 2+","location":"Jeugdhoek","start":"2026-03-06T09:00:00.000Z","week":"b_thisweek","branch":"OBA Van der Pek"},{"id":"|evenementen|2067825","title":"Online Taalcafé","location":"OBA Online","start":"2026-03-06T09:30:00.000Z","week":"b_thisweek","branch":"OBA Van der Pek"},{"id":"|evenementen|2148236","title":"Conversatielessen","location":"Open ruimte","start":"2026-03-09T09:00:00.000Z","week":"c_nextweek","branch":"OBA Van der Pek"},{"id":"|evenementen|2067760","title":"Online Meeleesclub","location":"OBA Online","start":"2026-03-10T09:30:00.000Z","week":"c_nextweek","branch":"OBA Van der Pek"},{"id":"|evenementen|2140260","title":"Voorleespret 4+","location":"Jeugdhoek","start":"2026-03-11T14:30:00.000Z","week":"c_nextweek","branch":"OBA Van der Pek"},{"id":"|evenementen|2133885","title":"Boek op schoot 2+","location":"Jeugdhoek","start":"2026-03-13T09:00:00.000Z","week":"c_nextweek","branch":"OBA Van der Pek"},{"id":"|evenementen|2067826","title":"Online Taalcafé","location":"OBA Online","start":"2026-03-13T09:30:00.000Z","week":"c_nextweek","branch":"OBA Van der Pek"}],"counts":{"b_thisweek":3,"c_nextweek":5},"error":null}