{"branch":"OBA Geuzenveld","lastSync":1773068024600,"total":10,"pages":2,"items":[{"id":"|evenementen|2067128","title":"Taaltafel met de Buurtcampus","location":"Open ruimte","start":"2026-03-10T09:00:00.000Z","week":"b_thisweek","branch":"OBA Geuzenveld"},{"id":"|evenementen|2067760","title":"Online Meeleesclub","location":"OBA Online","start":"2026-03-10T09:30:00.000Z","week":"b_thisweek","branch":"OBA Geuzenveld"},{"id":"|evenementen|2129550","title":"Spreekuur: Hulp bij digitaal","location":"Open ruimte","start":"2026-03-11T09:00:00.000Z","week":"b_thisweek","branch":"OBA Geuzenveld"},{"id":"|evenementen|2152709","title":"Boek op schoot 2+","location":"Jeugdhoek","start":"2026-03-13T09:00:00.000Z","week":"b_thisweek","branch":"OBA Geuzenveld"},{"id":"|evenementen|2067826","title":"Online Taalcafé","location":"OBA Online","start":"2026-03-13T09:30:00.000Z","week":"b_thisweek","branch":"OBA Geuzenveld"},{"id":"|evenementen|2067129","title":"Taaltafel met de Buurtcampus","location":"Open ruimte","start":"2026-03-17T09:00:00.000Z","week":"c_nextweek","branch":"OBA Geuzenveld"},{"id":"|evenementen|2067761","title":"Online Meeleesclub","location":"OBA Online","start":"2026-03-17T09:30:00.000Z","week":"c_nextweek","branch":"OBA Geuzenveld"},{"id":"|evenementen|2129551","title":"Spreekuur: Hulp bij digitaal","location":"Open ruimte","start":"2026-03-18T09:00:00.000Z","week":"c_nextweek","branch":"OBA Geuzenveld"},{"id":"|evenementen|2152710","title":"Boek op schoot 2+","location":"Jeugdhoek","start":"2026-03-20T09:00:00.000Z","week":"c_nextweek","branch":"OBA Geuzenveld"},{"id":"|evenementen|2067827","title":"Online Taalcafé","location":"OBA Online","start":"2026-03-20T09:30:00.000Z","week":"c_nextweek","branch":"OBA Geuzenveld"}],"counts":{"b_thisweek":5,"c_nextweek":5},"error":null}