{"branch":"OBA Next Lab Kraaiennest","lastSync":1770915738374,"total":3,"pages":1,"items":[{"id":"|evenementen|2160979","title":"Spoken word-workshop “Liefs, Mezelf”","location":"Roots library","start":"2026-02-14T11:00:00.000Z","week":"b_thisweek","branch":"OBA Next Lab Kraaiennest"},{"id":"|evenementen|2100485","title":"Maakplaats | Kunst en techniek | De groene makers","location":"Maakplaats","start":"2026-02-16T13:30:00.000Z","week":"c_nextweek","branch":"OBA Next Lab Kraaiennest"},{"id":"|evenementen|2100492","title":"Maakplaats | Digitale fabricage | Ruimtepioniers","location":"Maakplaats","start":"2026-02-18T13:30:00.000Z","week":"c_nextweek","branch":"OBA Next Lab Kraaiennest"}],"counts":{"b_thisweek":1,"c_nextweek":2},"error":null}