{"branch":"OBA punt Ganzenhoef","lastSync":1770009888083,"total":10,"pages":2,"items":[{"id":"|evenementen|2067742","title":"Online Meeleesclub","location":"OBA Online","start":"2026-02-03T09:30:00.000Z","week":"b_thisweek","branch":"OBA punt Ganzenhoef"},{"id":"|evenementen|2131103","title":"Boek op schoot 2+","location":"Jeugdhoek","start":"2026-02-04T09:00:00.000Z","week":"b_thisweek","branch":"OBA punt Ganzenhoef"},{"id":"|evenementen|2062209","title":"Spreekuur: Hulp bij digitaal","location":"Open ruimte","start":"2026-02-04T12:30:00.000Z","week":"b_thisweek","branch":"OBA punt Ganzenhoef"},{"id":"|evenementen|2067821","title":"Online Taalcafé","location":"OBA Online","start":"2026-02-06T09:30:00.000Z","week":"b_thisweek","branch":"OBA punt Ganzenhoef"},{"id":"|evenementen|2155596","title":"Opening expositie 'Een woning bouwen doe je samen'","location":"Atrium","start":"2026-02-06T13:45:00.000Z","week":"b_thisweek","branch":"OBA punt Ganzenhoef"},{"id":"|evenementen|2155791","title":"Expositie 'Een woning bouwen doe je samen'","location":"Atrium","start":"2026-02-06T16:00:00.000Z","week":"b_thisweek","branch":"OBA punt Ganzenhoef"},{"id":"|evenementen|2067743","title":"Online Meeleesclub","location":"OBA Online","start":"2026-02-10T09:30:00.000Z","week":"c_nextweek","branch":"OBA punt Ganzenhoef"},{"id":"|evenementen|2131104","title":"Boek op schoot 2+","location":"Jeugdhoek","start":"2026-02-11T09:00:00.000Z","week":"c_nextweek","branch":"OBA punt Ganzenhoef"},{"id":"|evenementen|2062210","title":"Spreekuur: Hulp bij digitaal","location":"Open ruimte","start":"2026-02-11T12:30:00.000Z","week":"c_nextweek","branch":"OBA punt Ganzenhoef"},{"id":"|evenementen|2067822","title":"Online Taalcafé","location":"OBA Online","start":"2026-02-13T09:30:00.000Z","week":"c_nextweek","branch":"OBA punt Ganzenhoef"}],"counts":{"b_thisweek":6,"c_nextweek":4},"error":null}