{"branch":"OBA Bijlmer","lastSync":1781174397002,"total":20,"pages":3,"items":[{"id":"|evenementen|2238116","title":"Herstelhuis Inloopspreekuur","location":"De trap en Atrium en Groene Nissen","start":"2026-06-11T07:30:00.000Z","week":"b_thisweek","branch":"OBA Bijlmer"},{"id":"|evenementen|2062173","title":"Spreekuur: Hulp bij digitaal","location":"Florijn","start":"2026-06-11T08:00:00.000Z","week":"b_thisweek","branch":"OBA Bijlmer"},{"id":"|evenementen|2185032","title":"Cursus: Omgaan met stress","location":"Daalwijk","start":"2026-06-11T08:00:00.000Z","week":"b_thisweek","branch":"OBA Bijlmer"},{"id":"|evenementen|2201460","title":"Haak- & breiclub Bijlmerplein","location":"De trap en Atrium en Groene Nissen","start":"2026-06-11T09:00:00.000Z","week":"b_thisweek","branch":"OBA Bijlmer"},{"id":"|evenementen|2201365","title":"Spreekuur onderwijs","location":"De trap en Atrium en Groene Nissen","start":"2026-06-11T13:00:00.000Z","week":"b_thisweek","branch":"OBA Bijlmer"},{"id":"|evenementen|2131174","title":"Boek op schoot 2+","location":"Voorleeshoek Bims","start":"2026-06-12T08:00:00.000Z","week":"b_thisweek","branch":"OBA Bijlmer"},{"id":"|evenementen|2126620","title":"Cursus: Digivitaler (bijeenkomst 2)","location":"Daalwijk en Guldenkruis","start":"2026-06-12T12:00:00.000Z","week":"b_thisweek","branch":"OBA Bijlmer"},{"id":"|evenementen|2062119","title":"Spreekuur: Hulp bij digitaal","location":"Florijn","start":"2026-06-16T08:00:00.000Z","week":"c_nextweek","branch":"OBA Bijlmer"},{"id":"|evenementen|2108733","title":"Spreekuur Taalconsulent","location":"Hoptille","start":"2026-06-16T08:00:00.000Z","week":"c_nextweek","branch":"OBA Bijlmer"},{"id":"|evenementen|2067622","title":"Taalcafé","location":"Daalwijk en Guldenkruis","start":"2026-06-17T08:00:00.000Z","week":"c_nextweek","branch":"OBA Bijlmer"},{"id":"|evenementen|2194269","title":"Zorg en Welzijn inloopspreekuur","location":"Hoptille","start":"2026-06-17T08:00:00.000Z","week":"c_nextweek","branch":"OBA Bijlmer"},{"id":"|evenementen|2067677","title":"Meeleesclub","location":"Daalwijk en Guldenkruis","start":"2026-06-17T11:00:00.000Z","week":"c_nextweek","branch":"OBA Bijlmer"},{"id":"|evenementen|2185033","title":"Cursus: Omgaan met stress","location":"Daalwijk","start":"2026-06-18T08:00:00.000Z","week":"c_nextweek","branch":"OBA Bijlmer"},{"id":"|evenementen|2201461","title":"Haak- & breiclub Bijlmerplein","location":"De trap en Atrium en Groene Nissen","start":"2026-06-18T09:00:00.000Z","week":"c_nextweek","branch":"OBA Bijlmer"},{"id":"|evenementen|2201369","title":"Spreekuur onderwijs","location":"De trap en Atrium en Groene Nissen","start":"2026-06-18T13:00:00.000Z","week":"c_nextweek","branch":"OBA Bijlmer"},{"id":"|evenementen|2131175","title":"Boek op schoot 2+","location":"Voorleeshoek Bims","start":"2026-06-19T08:00:00.000Z","week":"c_nextweek","branch":"OBA Bijlmer"},{"id":"|evenementen|2126621","title":"Cursus: Digivitaler (bijeenkomst 3)","location":"Daalwijk en Guldenkruis","start":"2026-06-19T12:00:00.000Z","week":"c_nextweek","branch":"OBA Bijlmer"},{"id":"|evenementen|2211179","title":"Mama Café Bijlmer","location":"Voorleeshoek Bims","start":"2026-06-20T08:30:00.000Z","week":"c_nextweek","branch":"OBA Bijlmer"},{"id":"|evenementen|2227541","title":"Keti Koti special: Samen tegen racisme","location":"Daalwijk en Guldenkruis","start":"2026-06-21T12:30:00.000Z","week":"c_nextweek","branch":"OBA Bijlmer"},{"id":"|evenementen|2240941","title":"Keti Koti creatieve workshop 6+","location":"Voorleeshoek Bims","start":"2026-06-21T13:00:00.000Z","week":"c_nextweek","branch":"OBA Bijlmer"}],"counts":{"b_thisweek":7,"c_nextweek":13},"error":null}