{"branch":"OBA Molenwijk","lastSync":1779472436814,"total":13,"pages":2,"items":[{"id":"|evenementen|2133847","title":"Boek op schoot 2+","location":"Jeugdhoek","start":"2026-05-22T08:00:00.000Z","week":"b_thisweek","branch":"OBA Molenwijk"},{"id":"|evenementen|2220090","title":"Seniorenactiviteit: Filmmiddag","location":"Activiteiten ruimte","start":"2026-05-22T12:00:00.000Z","week":"b_thisweek","branch":"OBA Molenwijk"},{"id":"|evenementen|2141986","title":"Wijkclub Kunstmachine","location":"Maakplaats","start":"2026-05-22T13:00:00.000Z","week":"b_thisweek","branch":"OBA Molenwijk"},{"id":"|evenementen|2176814","title":"OBA Naaiatelier","location":"Maakplaats","start":"2026-05-23T08:00:00.000Z","week":"b_thisweek","branch":"OBA Molenwijk"},{"id":"|evenementen|2176902","title":"Maakplaats | Kunst en techniek | Paint your motto!","location":"Maakplaats","start":"2026-05-25T12:30:00.000Z","week":"c_nextweek","branch":"OBA Molenwijk"},{"id":"|evenementen|2067167","title":"Taalcafé","location":"Activiteiten ruimte","start":"2026-05-26T08:00:00.000Z","week":"c_nextweek","branch":"OBA Molenwijk"},{"id":"|evenementen|2204478","title":"Maakplaats | Cinekid | Hoe echt is wat je ziet?","location":"Maakplaats","start":"2026-05-27T13:00:00.000Z","week":"c_nextweek","branch":"OBA Molenwijk"},{"id":"|evenementen|2047564","title":"Oefenuur","location":"Activiteiten ruimte","start":"2026-05-28T11:30:00.000Z","week":"c_nextweek","branch":"OBA Molenwijk"},{"id":"|evenementen|2047595","title":"Spreekuur: Hulp bij digitaal","location":"Activiteiten ruimte","start":"2026-05-28T11:30:00.000Z","week":"c_nextweek","branch":"OBA Molenwijk"},{"id":"|evenementen|2176847","title":"Maakplaats | Maak je buurt | De Waanzinnige Flat","location":"Maakplaats","start":"2026-05-28T12:30:00.000Z","week":"c_nextweek","branch":"OBA Molenwijk"},{"id":"|evenementen|2133849","title":"Boek op schoot 2+","location":"Jeugdhoek","start":"2026-05-29T08:00:00.000Z","week":"c_nextweek","branch":"OBA Molenwijk"},{"id":"|evenementen|2141987","title":"Wijkclub Kunstmachine","location":"Maakplaats","start":"2026-05-29T13:00:00.000Z","week":"c_nextweek","branch":"OBA Molenwijk"},{"id":"|evenementen|2176815","title":"OBA Naaiatelier","location":"Maakplaats","start":"2026-05-30T08:00:00.000Z","week":"c_nextweek","branch":"OBA Molenwijk"}],"counts":{"b_thisweek":4,"c_nextweek":9},"error":null}