{"branch":"OBA Slotermeer","lastSync":1771712886915,"total":13,"pages":2,"items":[{"id":"|evenementen|2100006","title":"OBA Naaiatelier","location":"Maakplaats","start":"2026-02-21T09:00:00.000Z","week":"b_thisweek","branch":"OBA Slotermeer"},{"id":"|evenementen|2067026","title":"The Leopard Society Fantasy Boek- en Performanceclub","location":"Jeugdhoek Pinokkio","start":"2026-02-23T15:00:00.000Z","week":"c_nextweek","branch":"OBA Slotermeer"},{"id":"|evenementen|2061822","title":"Spreekuur: Hulp bij digitaal","location":"Broedplaats","start":"2026-02-24T09:00:00.000Z","week":"c_nextweek","branch":"OBA Slotermeer"},{"id":"|evenementen|2066241","title":"Oefenuur","location":"Broedplaats","start":"2026-02-24T09:00:00.000Z","week":"c_nextweek","branch":"OBA Slotermeer"},{"id":"|evenementen|2067758","title":"Online Meeleesclub","location":"OBA Online","start":"2026-02-24T09:30:00.000Z","week":"c_nextweek","branch":"OBA Slotermeer"},{"id":"|evenementen|2067341","title":"Meeleesclub","location":"Broedplaats","start":"2026-02-25T09:00:00.000Z","week":"c_nextweek","branch":"OBA Slotermeer"},{"id":"|evenementen|2067070","title":"Taalcafé","location":"Broedplaats","start":"2026-02-26T09:00:00.000Z","week":"c_nextweek","branch":"OBA Slotermeer"},{"id":"|evenementen|2126528","title":"Cursus: Digivitaler (bijeenkomst 1)","location":"Broedplaats","start":"2026-02-26T13:00:00.000Z","week":"c_nextweek","branch":"OBA Slotermeer"},{"id":"|evenementen|2135271","title":"Spreekuur: Grip op je geld","location":"Open ruimte","start":"2026-02-27T08:15:00.000Z","week":"c_nextweek","branch":"OBA Slotermeer"},{"id":"|evenementen|2133739","title":"Boek op schoot 2+","location":"Jeugdhoek Pinokkio","start":"2026-02-27T09:00:00.000Z","week":"c_nextweek","branch":"OBA Slotermeer"},{"id":"|evenementen|2067824","title":"Online Taalcafé","location":"OBA Online","start":"2026-02-27T09:30:00.000Z","week":"c_nextweek","branch":"OBA Slotermeer"},{"id":"|evenementen|2104905","title":"Voorleesatelier 5+","location":"Jeugdhoek Pinokkio","start":"2026-02-27T14:30:00.000Z","week":"c_nextweek","branch":"OBA Slotermeer"},{"id":"|evenementen|2100007","title":"OBA Naaiatelier","location":"Maakplaats","start":"2026-02-28T09:00:00.000Z","week":"c_nextweek","branch":"OBA Slotermeer"}],"counts":{"b_thisweek":1,"c_nextweek":12},"error":null}