{"branch":"OBA Ouderkerk","lastSync":1768559279012,"total":6,"pages":1,"items":[{"id":"|evenementen|2067818","title":"Online Taalcafé","location":"OBA Online","start":"2026-01-16T09:30:00.000Z","week":"b_thisweek","branch":"OBA Ouderkerk"},{"id":"|evenementen|2067740","title":"Online Meeleesclub","location":"OBA Online","start":"2026-01-20T09:30:00.000Z","week":"c_nextweek","branch":"OBA Ouderkerk"},{"id":"|evenementen|2136426","title":"Voorleesontbijt - De Nationale Voorleesdagen 2+","location":"Werkplekken","start":"2026-01-21T09:00:00.000Z","week":"c_nextweek","branch":"OBA Ouderkerk"},{"id":"|evenementen|2134133","title":"Boek op schoot 2+","location":"Open ruimte","start":"2026-01-22T09:30:00.000Z","week":"c_nextweek","branch":"OBA Ouderkerk"},{"id":"|evenementen|2134778","title":"Voorleesatelier 5+","location":"Open ruimte","start":"2026-01-22T14:30:00.000Z","week":"c_nextweek","branch":"OBA Ouderkerk"},{"id":"|evenementen|2067819","title":"Online Taalcafé","location":"OBA Online","start":"2026-01-23T09:30:00.000Z","week":"c_nextweek","branch":"OBA Ouderkerk"}],"counts":{"b_thisweek":1,"c_nextweek":5},"error":null}