{"branch":"OBA Staatsliedenbuurt","lastSync":1767882496735,"total":6,"pages":1,"items":[{"id":"|evenementen|2139477","title":"OBA Naaiatelier","location":"Maakplaats","start":"2026-01-09T09:00:00.000Z","week":"b_thisweek","branch":"OBA Staatsliedenbuurt"},{"id":"|evenementen|2067817","title":"Online Taalcafé","location":"OBA Online","start":"2026-01-09T09:30:00.000Z","week":"b_thisweek","branch":"OBA Staatsliedenbuurt"},{"id":"|evenementen|2067739","title":"Online Meeleesclub","location":"OBA Online","start":"2026-01-13T09:30:00.000Z","week":"c_nextweek","branch":"OBA Staatsliedenbuurt"},{"id":"|evenementen|2100609","title":"Maakplaats | Kunst en techniek | Textiellab","location":"Maakplaats","start":"2026-01-13T14:00:00.000Z","week":"c_nextweek","branch":"OBA Staatsliedenbuurt"},{"id":"|evenementen|2139478","title":"OBA Naaiatelier","location":"Maakplaats","start":"2026-01-16T09:00:00.000Z","week":"c_nextweek","branch":"OBA Staatsliedenbuurt"},{"id":"|evenementen|2067818","title":"Online Taalcafé","location":"OBA Online","start":"2026-01-16T09:30:00.000Z","week":"c_nextweek","branch":"OBA Staatsliedenbuurt"}],"counts":{"b_thisweek":2,"c_nextweek":4},"error":null}