{"branch":"OBA Spaarndammerbuurt","lastSync":1777183672916,"total":2,"pages":1,"items":[{"id":"|evenementen|2105955","title":"Voorleesatelier 5+","location":"Jeugdhoek Nijntje","start":"2026-04-29T13:30:00.000Z","week":"c_nextweek","branch":"OBA Spaarndammerbuurt"},{"id":"|evenementen|2190306","title":"Seniorenactiviteit: Literair Atelier à GoGo","location":"Open ruimte","start":"2026-05-01T09:00:00.000Z","week":"c_nextweek","branch":"OBA Spaarndammerbuurt"}],"counts":{"b_thisweek":0,"c_nextweek":2},"error":null}