{"branch":"OBA Geuzenveld","lastSync":1769769472987,"total":7,"pages":1,"items":[{"id":"|evenementen|2152703","title":"Boek op schoot 2+","location":"Jeugdhoek","start":"2026-01-30T09:00:00.000Z","week":"b_thisweek","branch":"OBA Geuzenveld"},{"id":"|evenementen|2067820","title":"Online Taalcafé","location":"OBA Online","start":"2026-01-30T09:30:00.000Z","week":"b_thisweek","branch":"OBA Geuzenveld"},{"id":"|evenementen|2067123","title":"Taaltafel met de Buurtcampus","location":"Open ruimte","start":"2026-02-03T09:00:00.000Z","week":"c_nextweek","branch":"OBA Geuzenveld"},{"id":"|evenementen|2067742","title":"Online Meeleesclub","location":"OBA Online","start":"2026-02-03T09:30:00.000Z","week":"c_nextweek","branch":"OBA Geuzenveld"},{"id":"|evenementen|2129546","title":"Spreekuur: Hulp bij digitaal","location":"Open ruimte","start":"2026-02-04T09:00:00.000Z","week":"c_nextweek","branch":"OBA Geuzenveld"},{"id":"|evenementen|2152704","title":"Boek op schoot 2+","location":"Jeugdhoek","start":"2026-02-06T09:00:00.000Z","week":"c_nextweek","branch":"OBA Geuzenveld"},{"id":"|evenementen|2067821","title":"Online Taalcafé","location":"OBA Online","start":"2026-02-06T09:30:00.000Z","week":"c_nextweek","branch":"OBA Geuzenveld"}],"counts":{"b_thisweek":2,"c_nextweek":5},"error":null}